ccr/__init__.py
ccr/analyzer.py
ccr/cli.py
context_confidence_rating-0.1.2.dist-info/licenses/LICENSE
context_confidence_rating-0.1.2.dist-info/METADATA
context_confidence_rating-0.1.2.dist-info/WHEEL
context_confidence_rating-0.1.2.dist-info/entry_points.txt
context_confidence_rating-0.1.2.dist-info/top_level.txt
context_confidence_rating-0.1.2.dist-info/RECORD
