Metadata-Version: 2.4
Name: context-confidence-rating
Version: 0.1.2
Summary: Calculate context-aware confidence scores for security findings
Home-page: https://github.com/secuardenai/context-confidence-rating
Author: Secuarden Team
Author-email: Secuarden Team <hello@secuarden.com>
License: MIT
Project-URL: Homepage, https://github.com/secuarden/context-confidence-rating
Project-URL: Documentation, https://github.com/secuarden/context-confidence-rating#readme
Project-URL: Repository, https://github.com/secuarden/context-confidence-rating
Project-URL: Bug Reports, https://github.com/secuarden/context-confidence-rating/issues
Keywords: security,vulnerability,context,confidence,sast,analysis
Classifier: Development Status :: 4 - Beta
Classifier: Intended Audience :: Developers
Classifier: Topic :: Security
Classifier: Topic :: Software Development :: Quality Assurance
Classifier: License :: OSI Approved :: MIT License
Classifier: Programming Language :: Python :: 3
Classifier: Programming Language :: Python :: 3.8
Classifier: Programming Language :: Python :: 3.9
Classifier: Programming Language :: Python :: 3.10
Classifier: Programming Language :: Python :: 3.11
Classifier: Programming Language :: Python :: 3.12
Requires-Python: >=3.8
License-File: LICENSE
Provides-Extra: dev
Requires-Dist: pytest>=7.0; extra == "dev"
Requires-Dist: pytest-cov>=4.0; extra == "dev"
Requires-Dist: black>=23.0; extra == "dev"
Requires-Dist: flake8>=6.0; extra == "dev"
Dynamic: author
Dynamic: home-page
Dynamic: license-file
Dynamic: requires-python
